{"level":30,"time":1683732256635,"pid":14867,"hostname":"Gilberts-MacBook-Pro.local","msg":"Logged in as Nubbless#9047"}
{"level":30,"time":1683732301301,"pid":14946,"hostname":"Gilberts-MacBook-Pro.local","msg":"Logged in as @Nubbless#9047"}
{"level":30,"time":1683732482528,"pid":15092,"hostname":"Gilberts-MacBook-Pro.local","msg":"Logged in as @Nubbless#9047"}
{"level":30,"time":1683732675653,"pid":15211,"hostname":"Gilberts-MacBook-Pro.local","msg":"Logged in as @Nubbless#9047"}
{"level":30,"time":1683733535658,"pid":15856,"hostname":"Gilberts-MacBook-Pro.local","msg":"Logged in as @Nubbless#9047"}
{"level":30,"time":1683733602454,"pid":15930,"hostname":"Gilberts-MacBook-Pro.local","msg":"Logged in as @Nubbless#9047"}
{"level":30,"time":1683733693559,"pid":16096,"hostname":"Gilberts-MacBook-Pro.local","msg":"Logged in as @Nubbless#9047"}
{"level":30,"time":1683733911405,"pid":16220,"hostname":"Gilberts-MacBook-Pro.local","msg":"Logged in as @Nubbless#9047"}
{"level":30,"time":1683734042064,"pid":16430,"hostname":"Gilberts-MacBook-Pro.local","msg":"Logged in as @Nubbless#9047"}
{"level":30,"time":1683735136881,"pid":16743,"hostname":"Gilberts-MacBook-Pro.local","msg":"Logged in as @Nubbless#9047"}
{"level":30,"time":1683758973064,"pid":18058,"hostname":"Gilberts-MacBook-Pro.local","msg":"Logged in as @Nubbless#9047"}
{"level":30,"time":1683759324149,"pid":18250,"hostname":"Gilberts-MacBook-Pro.local","msg":"Logged in as @Nubbless#9047"}
{"level":30,"time":1683759432900,"pid":18310,"hostname":"Gilberts-MacBook-Pro.local","msg":"Logged in as @Nubbless#9047"}
{"level":30,"time":1683759488093,"pid":18373,"hostname":"Gilberts-MacBook-Pro.local","msg":"Logged in as @Nubbless#9047"}
{"level":30,"time":1683764773250,"pid":19293,"hostname":"Gilberts-MacBook-Pro.local","msg":"Logged in as @Nubbless#9047"}
{"level":30,"time":1683765332785,"pid":19417,"hostname":"Gilberts-MacBook-Pro.local","msg":"Logged in as @Nubbless#9047"}
{"level":30,"time":1683818981971,"pid":22837,"hostname":"Gilberts-MacBook-Pro.local","msg":"Logged in as @Nubbless#9047"}
{"level":30,"time":1683819083347,"pid":22932,"hostname":"Gilberts-MacBook-Pro.local","msg":"Logged in as @Nubbless#9047"}
{"level":30,"time":1683819115707,"pid":22995,"hostname":"Gilberts-MacBook-Pro.local","msg":"Logged in as @Nubbless#9047"}
{"level":30,"time":1683819241049,"pid":23072,"hostname":"Gilberts-MacBook-Pro.local","msg":"Logged in as @Nubbless#9047"}
{"level":30,"time":1683819400516,"pid":23267,"hostname":"Gilberts-MacBook-Pro.local","msg":"Logged in as @Nubbless#9047"}
